redlistapi/Assessment.py
redlistapi/Interfaces.py
redlistapi/__init__.py
redlistapi/_version.py
redlistapi/api.py
redlistapi-0.1.2.dist-info/licenses/LICENSE
redlistapi-0.1.2.dist-info/METADATA
redlistapi-0.1.2.dist-info/WHEEL
redlistapi-0.1.2.dist-info/top_level.txt
redlistapi-0.1.2.dist-info/RECORD
