Metadata-Version: 2.4
Name: redlistapi
Version: 0.1.2
Summary: A Python client for the IUCN Red List API
Author-email: Daniele Baisero <daniele.baisero@gmail.com>
License-Expression: MIT
Project-URL: homepage, https://gitlab.com/daniele.baisero/redlistapi
Project-URL: repository, https://gitlab.com/daniele.baisero/redlistapi
Project-URL: bugtracker, https://gitlab.com/daniele.baisero/redlistapi/issues
Keywords: IUCN,Red List,Red-List,KBA,Key Biodiversity Area,Key Biodiversity Areas
Requires-Python: >=3.12
License-File: LICENSE
Requires-Dist: requests
Requires-Dist: python-dotenv
Requires-Dist: PyYAML
Requires-Dist: numpy
Requires-Dist: pandas
Requires-Dist: tqdm
Provides-Extra: spatial
Requires-Dist: shapely; extra == "spatial"
Requires-Dist: geopandas; extra == "spatial"
Requires-Dist: geojson; extra == "spatial"
Requires-Dist: gdal; extra == "spatial"
Provides-Extra: test
Requires-Dist: pytest; extra == "test"
Requires-Dist: ruff; extra == "test"
Dynamic: license-file
